[{"model": "admin.logentry", "pk": 1, "fields": {"action_time": "2021-12-11T18:03:17.576Z", "user": 1, "content_type": 4, "object_id": "2", "object_repr": "leon", "action_flag": 1, "change_message": "[{\"added\": {}}]"}}, {"model": "admin.logentry", "pk": 2, "fields": {"action_time": "2021-12-11T18:04:51.298Z", "user": 1, "content_type": 8, "object_id": "2", "object_repr": "pytonska_1 belonging to 1, located in kitchen", "action_flag": 1, "change_message": "[{\"added\": {}}]"}}, {"model": "admin.logentry", "pk": 3, "fields": {"action_time": "2021-12-11T18:07:15.738Z", "user": 1, "content_type": 8, "object_id": "3", "object_repr": "pytonska_3 belonging to 1, located in kitchen", "action_flag": 1, "change_message": "[{\"added\": {}}]"}}, {"model": "admin.logentry", "pk": 4, "fields": {"action_time": "2021-12-11T18:07:47.270Z", "user": 1, "content_type": 8, "object_id": "4", "object_repr": "pytonska_3 belonging to 2, located in bathroom", "action_flag": 1, "change_message": "[{\"added\": {}}]"}}, {"model": "admin.logentry", "pk": 5, "fields": {"action_time": "2021-12-11T18:08:34.700Z", "user": 1, "content_type": 9, "object_id": "1", "object_repr": "1 belonging to 2, at 2021-12-11 18:08:25+00:00", "action_flag": 1, "change_message": "[{\"added\": {}}]"}}, {"model": "admin.logentry", "pk": 6, "fields": {"action_time": "2021-12-11T18:08:52.823Z", "user": 1, "content_type": 9, "object_id": "2", "object_repr": "2 belonging to 2, at 2021-12-11 18:08:49+00:00", "action_flag": 1, "change_message": "[{\"added\": {}}]"}}, {"model": "admin.logentry", "pk": 7, "fields": {"action_time": "2021-12-11T18:09:08.584Z", "user": 1, "content_type": 9, "object_id": "3", "object_repr": "3 belonging to 2, at 2021-12-11 18:09:05+00:00", "action_flag": 1, "change_message": "[{\"added\": {}}]"}}, {"model": "admin.logentry", "pk": 8, "fields": {"action_time": "2021-12-11T18:09:28.315Z", "user": 1, "content_type": 9, "object_id": "4", "object_repr": "4 belonging to 3, at 2021-12-11 18:09:26+00:00", "action_flag": 1, "change_message": "[{\"added\": {}}]"}}, {"model": "admin.logentry", "pk": 9, "fields": {"action_time": "2021-12-11T18:09:49.783Z", "user": 1, "content_type": 9, "object_id": "5", "object_repr": "5 belonging to 3, at 2021-12-11 18:09:46+00:00", "action_flag": 1, "change_message": "[{\"added\": {}}]"}}, {"model": "admin.logentry", "pk": 10, "fields": {"action_time": "2021-12-11T18:10:02.510Z", "user": 1, "content_type": 9, "object_id": "6", "object_repr": "6 belonging to 4, at 2021-12-11 18:09:59+00:00", "action_flag": 1, "change_message": "[{\"added\": {}}]"}}, {"model": "admin.logentry", "pk": 11, "fields": {"action_time": "2021-12-11T20:15:19.863Z", "user": 1, "content_type": 9, "object_id": "7", "object_repr": "7 belonging to 4, at 2021-12-11 20:15:16+00:00", "action_flag": 1, "change_message": "[{\"added\": {}}]"}}, {"model": "admin.logentry", "pk": 12, "fields": {"action_time": "2021-12-11T20:15:35.510Z", "user": 1, "content_type": 9, "object_id": "8", "object_repr": "8 belonging to 4, at 2021-12-11 20:15:32+00:00", "action_flag": 1, "change_message": "[{\"added\": {}}]"}}, {"model": "auth.permission", "pk": 1, "fields": {"name": "Can add log entry", "content_type": 1, "codename": "add_logentry"}}, {"model": "auth.permission", "pk": 2, "fields": {"name": "Can change log entry", "content_type": 1, "codename": "change_logentry"}}, {"model": "auth.permission", "pk": 3, "fields": {"name": "Can delete log entry", "content_type": 1, "codename": "delete_logentry"}}, {"model": "auth.permission", "pk": 4, "fields": {"name": "Can view log entry", "content_type": 1, "codename": "view_logentry"}}, {"model": "auth.permission", "pk": 5, "fields": {"name": "Can add permission", "content_type": 2, "codename": "add_permission"}}, {"model": "auth.permission", "pk": 6, "fields": {"name": "Can change permission", "content_type": 2, "codename": "change_permission"}}, {"model": "auth.permission", "pk": 7, "fields": {"name": "Can delete permission", "content_type": 2, "codename": "delete_permission"}}, {"model": "auth.permission", "pk": 8, "fields": {"name": "Can view permission", "content_type": 2, "codename": "view_permission"}}, {"model": "auth.permission", "pk": 9, "fields": {"name": "Can add group", "content_type": 3, "codename": "add_group"}}, {"model": "auth.permission", "pk": 10, "fields": {"name": "Can change group", "content_type": 3, "codename": "change_group"}}, {"model": "auth.permission", "pk": 11, "fields": {"name": "Can delete group", "content_type": 3, "codename": "delete_group"}}, {"model": "auth.permission", "pk": 12, "fields": {"name": "Can view group", "content_type": 3, "codename": "view_group"}}, {"model": "auth.permission", "pk": 13, "fields": {"name": "Can add user", "content_type": 4, "codename": "add_user"}}, {"model": "auth.permission", "pk": 14, "fields": {"name": "Can change user", "content_type": 4, "codename": "change_user"}}, {"model": "auth.permission", "pk": 15, "fields": {"name": "Can delete user", "content_type": 4, "codename": "delete_user"}}, {"model": "auth.permission", "pk": 16, "fields": {"name": "Can view user", "content_type": 4, "codename": "view_user"}}, {"model": "auth.permission", "pk": 17, "fields": {"name": "Can add content type", "content_type": 5, "codename": "add_contenttype"}}, {"model": "auth.permission", "pk": 18, "fields": {"name": "Can change content type", "content_type": 5, "codename": "change_contenttype"}}, {"model": "auth.permission", "pk": 19, "fields": {"name": "Can delete content type", "content_type": 5, "codename": "delete_contenttype"}}, {"model": "auth.permission", "pk": 20, "fields": {"name": "Can view content type", "content_type": 5, "codename": "view_contenttype"}}, {"model": "auth.permission", "pk": 21, "fields": {"name": "Can add session", "content_type": 6, "codename": "add_session"}}, {"model": "auth.permission", "pk": 22, "fields": {"name": "Can change session", "content_type": 6, "codename": "change_session"}}, {"model": "auth.permission", "pk": 23, "fields": {"name": "Can delete session", "content_type": 6, "codename": "delete_session"}}, {"model": "auth.permission", "pk": 24, "fields": {"name": "Can view session", "content_type": 6, "codename": "view_session"}}, {"model": "auth.permission", "pk": 25, "fields": {"name": "Can add product model", "content_type": 7, "codename": "add_productmodel"}}, {"model": "auth.permission", "pk": 26, "fields": {"name": "Can change product model", "content_type": 7, "codename": "change_productmodel"}}, {"model": "auth.permission", "pk": 27, "fields": {"name": "Can delete product model", "content_type": 7, "codename": "delete_productmodel"}}, {"model": "auth.permission", "pk": 28, "fields": {"name": "Can view product model", "content_type": 7, "codename": "view_productmodel"}}, {"model": "auth.permission", "pk": 29, "fields": {"name": "Can add sensor model", "content_type": 8, "codename": "add_sensormodel"}}, {"model": "auth.permission", "pk": 30, "fields": {"name": "Can change sensor model", "content_type": 8, "codename": "change_sensormodel"}}, {"model": "auth.permission", "pk": 31, "fields": {"name": "Can delete sensor model", "content_type": 8, "codename": "delete_sensormodel"}}, {"model": "auth.permission", "pk": 32, "fields": {"name": "Can view sensor model", "content_type": 8, "codename": "view_sensormodel"}}, {"model": "auth.permission", "pk": 33, "fields": {"name": "Can add sensor value model", "content_type": 9, "codename": "add_sensorvaluemodel"}}, {"model": "auth.permission", "pk": 34, "fields": {"name": "Can change sensor value model", "content_type": 9, "codename": "change_sensorvaluemodel"}}, {"model": "auth.permission", "pk": 35, "fields": {"name": "Can delete sensor value model", "content_type": 9, "codename": "delete_sensorvaluemodel"}}, {"model": "auth.permission", "pk": 36, "fields": {"name": "Can view sensor value model", "content_type": 9, "codename": "view_sensorvaluemodel"}}, {"model": "auth.user", "pk": 1, "fields": {"password": "pbkdf2_sha256$260000$I4Yntm6znewA7oJQ9JfQ7E$YHy+Sau+WoOWoJ7kMhw/OsdUHxrufp4sHLjZU9yt7dk=", "last_login": "2021-12-11T18:00:54.247Z", "is_superuser": true, "username": "maurice", "first_name": "", "last_name": "", "email": "", "is_staff": true, "is_active": true, "date_joined": "2021-12-11T18:00:43.685Z", "groups": [], "user_permissions": []}}, {"model": "auth.user", "pk": 2, "fields": {"password": "pbkdf2_sha256$260000$RhCee2XVdazaLtPVokTrYx$DUpBMW34RIuG1fEZ+YAVLCdIHoyzTh82ZWUG2rjDVgI=", "last_login": null, "is_superuser": false, "username": "leon", "first_name": "", "last_name": "", "email": "", "is_staff": false, "is_active": true, "date_joined": "2021-12-11T18:03:17.154Z", "groups": [], "user_permissions": []}}, {"model": "contenttypes.contenttype", "pk": 1, "fields": {"app_label": "admin", "model": "logentry"}}, {"model": "contenttypes.contenttype", "pk": 2, "fields": {"app_label": "auth", "model": "permission"}}, {"model": "contenttypes.contenttype", "pk": 3, "fields": {"app_label": "auth", "model": "group"}}, {"model": "contenttypes.contenttype", "pk": 4, "fields": {"app_label": "auth", "model": "user"}}, {"model": "contenttypes.contenttype", "pk": 5, "fields": {"app_label": "contenttypes", "model": "contenttype"}}, {"model": "contenttypes.contenttype", "pk": 6, "fields": {"app_label": "sessions", "model": "session"}}, {"model": "contenttypes.contenttype", "pk": 7, "fields": {"app_label": "webshop_app", "model": "productmodel"}}, {"model": "contenttypes.contenttype", "pk": 8, "fields": {"app_label": "webshop_app", "model": "sensormodel"}}, {"model": "contenttypes.contenttype", "pk": 9, "fields": {"app_label": "webshop_app", "model": "sensorvaluemodel"}}, {"model": "sessions.session", "pk": "fmzefk995c7soew6mvx0mwkq8dhtrw61", "fields": {"session_data": ".eJxVjEEOwiAQRe_C2pAplCm4dO8ZyACDVA0kpV0Z765NutDtf-_9l_C0rcVvnRc_J3EWgzj9boHig-sO0p3qrcnY6rrMQe6KPGiX15b4eTncv4NCvXxrHDFxVhoni5C1I7CZlQNQyoUAyuQJHZtswEWKjDTgCFaTy8YQYhLvD8hIN1M:1mw6g2:E9fs_s4BLvaxr8-npu6Nf52tObPPYKltHP5KNU8mR0s", "expire_date": "2021-12-25T18:00:54.353Z"}}, {"model": "webshop_app.productmodel", "pk": 1, "fields": {"name": "Sensor_1", "price": 50, "img": "products/Sensor_1/1c956ae5454b4c8c6bfea6c346c06994.jpg", "description": "toller sensor"}}, {"model": "webshop_app.sensormodel", "pk": 2, "fields": {"user": 1, "product": 1, "location": "kitchen", "name": "pytonska_1", "ip_address": "192.168.2.100"}}, {"model": "webshop_app.sensormodel", "pk": 3, "fields": {"user": 1, "product": 1, "location": "kitchen", "name": "pytonska_3", "ip_address": "192.168.2.101"}}, {"model": "webshop_app.sensormodel", "pk": 4, "fields": {"user": 2, "product": 1, "location": "bathroom", "name": "pytonska_3", "ip_address": "192.168.2.102"}}, {"model": "webshop_app.sensorvaluemodel", "pk": 1, "fields": {"sensor": 2, "temp": 23.0, "hum": 80.0, "pres": 1000.0, "dt": "2021-12-11T18:08:25Z"}}, {"model": "webshop_app.sensorvaluemodel", "pk": 2, "fields": {"sensor": 2, "temp": 20.0, "hum": 20.0, "pres": 1001.0, "dt": "2021-12-11T18:08:49Z"}}, {"model": "webshop_app.sensorvaluemodel", "pk": 3, "fields": {"sensor": 2, "temp": 20.0, "hum": 20.0, "pres": 20.0, "dt": "2021-12-11T18:09:05Z"}}, {"model": "webshop_app.sensorvaluemodel", "pk": 4, "fields": {"sensor": 3, "temp": 10.0, "hum": 20.0, "pres": 30.0, "dt": "2021-12-11T18:09:26Z"}}, {"model": "webshop_app.sensorvaluemodel", "pk": 5, "fields": {"sensor": 3, "temp": 30.0, "hum": 2.0, "pres": 10.0, "dt": "2021-12-11T18:09:46Z"}}, {"model": "webshop_app.sensorvaluemodel", "pk": 6, "fields": {"sensor": 4, "temp": 30.0, "hum": 30.0, "pres": 3.0, "dt": "2021-12-11T18:09:59Z"}}, {"model": "webshop_app.sensorvaluemodel", "pk": 7, "fields": {"sensor": 4, "temp": 30.0, "hum": 50.0, "pres": 10.0, "dt": "2021-12-11T20:15:16Z"}}, {"model": "webshop_app.sensorvaluemodel", "pk": 8, "fields": {"sensor": 4, "temp": 20.0, "hum": 40.0, "pres": 30.0, "dt": "2021-12-11T20:15:32Z"}}]